CONTRIBUTING.rst
LICENSE
MANIFEST.in
README.rst
setup.cfg
setup.py
docs/Makefile
docs/conf.py
docs/contributing.rst
docs/index.rst
docs/installation.rst
docs/make.bat
docs/readme.rst
docs/usage.rst
pttagger/__init__.py
pttagger/dataset.py
pttagger/model.py
pttagger.egg-info/PKG-INFO
pttagger.egg-info/SOURCES.txt
pttagger.egg-info/dependency_links.txt
pttagger.egg-info/not-zip-safe
pttagger.egg-info/top_level.txt
tests/__init__.py
tests/test_dataset.py
tests/test_model.py