Metadata-Version: 1.1
Name: pttagger
Version: 0.1.1
Summary: Simple PyTorch-based tagger
Home-page: https://github.com/jun-harashima/pttagger
Author: Jun Harashima
Author-email: j.harashima@gmail.com
License: MIT license
Keywords: pttagger
Platform: UNKNOWN
Classifier: Development Status :: 2 - Pre-Alpha
Classifier: Intended Audience :: Developers
Classifier: License :: OSI Approved :: MIT License
Classifier: Natural Language :: English
Classifier: Programming Language :: Python :: 3
Classifier: Programming Language :: Python :: 3.5
Classifier: Programming Language :: Python :: 3.6
Classifier: Programming Language :: Python :: 3.7
